langchain_cfg_build/__init__.py
langchain_cfg_build/agent/__init__.py
langchain_cfg_build/agent/agent_builder.py
langchain_cfg_build/demo/__init__.py
langchain_cfg_build/demo/try_retrieve_qa.py
langchain_cfg_build/embed_db/__init__.py
langchain_cfg_build/embed_db/embed_db_loader.py
langchain_cfg_build/embed_db/embed_db_query_service.py
langchain_cfg_build/infra/__init__.py
langchain_cfg_build/infra/config.py
langchain_cfg_build/langchain_cfg_build_app.py
langchain_cfg_build/lcb_hi_service.py
langchain_cfg_build/llm/__init__.py
langchain_cfg_build/llm/enum_llm.py
langchain_cfg_build/obj/__init__.py
langchain_cfg_build/obj/cache_provider.py
langchain_cfg_build/prompt/__init__.py
langchain_cfg_build/prompt/enum_prompt.py
langchain_cfg_build/rag/__init__.py
langchain_cfg_build/rag/rag_service.py
langchain_cfg_build/tool/__init__.py
langchain_cfg_build/tool/tool_repository.py
langchain_cfg_build/tool/tool_utils.py
langchain_cfg_build/utils/__init__.py
langchain_cfg_build/utils/file_utils.py
langchain_cfg_build-0.1.13.dist-info/METADATA
langchain_cfg_build-0.1.13.dist-info/WHEEL
langchain_cfg_build-0.1.13.dist-info/RECORD
