Metadata-Version: 2.1
Name: langchain-cfg-build
Version: 0.1.13
Summary: 
Author: kirin
Author-email: kirin.chen1001@gmail.com
Requires-Python: >=3.11,<4.0
Classifier: Programming Language :: Python :: 3
Classifier: Programming Language :: Python :: 3.11
Classifier: Programming Language :: Python :: 3.12
Requires-Dist: chromadb (>=0.5.23,<0.6.0)
Requires-Dist: langchain (>=0.3.13,<0.4.0)
Requires-Dist: langchain-chroma (>=0.1.4,<0.2.0)
Requires-Dist: langchain-community (>=0.3.12,<0.4.0)
Requires-Dist: langchain-openai (>=0.2.13,<0.3.0)
Requires-Dist: python-dotenv (>=1.0.1,<2.0.0)
